odoo/addons/l10n_ro_partner_statement/README.rst
odoo/addons/l10n_ro_partner_statement/__init__.py
odoo/addons/l10n_ro_partner_statement/__manifest__.py
odoo/addons/l10n_ro_partner_statement/i18n/l10n_ro_partner_statement.pot
odoo/addons/l10n_ro_partner_statement/readme/CONTRIBUTORS.rst
odoo/addons/l10n_ro_partner_statement/readme/DESCRIPTION.rst
odoo/addons/l10n_ro_partner_statement/report/__init__.py
odoo/addons/l10n_ro_partner_statement/static/description/icon.png
odoo/addons/l10n_ro_partner_statement/static/description/index.html
odoo/addons/l10n_ro_partner_statement/tests/__init__.py
odoo/addons/l10n_ro_partner_statement/tests/test_activity_statement.py
odoo/addons/l10n_ro_partner_statement/views/activity_statement.xml
odoo/addons/l10n_ro_partner_statement/wizard/__init__.py
odoo/addons/l10n_ro_partner_statement/wizard/activity_statement_wizard.py
odoo/addons/l10n_ro_partner_statement/wizard/statement_wizard.xml
odoo13_addon_l10n_ro_partner_statement-13.0.1.0.1.dev22.dist-info/METADATA
odoo13_addon_l10n_ro_partner_statement-13.0.1.0.1.dev22.dist-info/WHEEL
odoo13_addon_l10n_ro_partner_statement-13.0.1.0.1.dev22.dist-info/top_level.txt
odoo13_addon_l10n_ro_partner_statement-13.0.1.0.1.dev22.dist-info/RECORD
